remarkov/__init__.py
remarkov/__main__.py
remarkov/cli.py
remarkov/error.py
remarkov/model.py
remarkov/persistance.py
remarkov/py.typed
remarkov/tokenizer.py
remarkov/types.py
remarkov-0.2.6.dist-info/LICENSE
remarkov-0.2.6.dist-info/METADATA
remarkov-0.2.6.dist-info/WHEEL
remarkov-0.2.6.dist-info/entry_points.txt
remarkov-0.2.6.dist-info/top_level.txt
remarkov-0.2.6.dist-info/RECORD
