Metadata-Version: 2.1
Name: remarkov
Version: 0.2.6
Summary: Generate text from text using Markov chains.
Home-page: https://github.com/lausek/remarkov
Author: lausek
Author-email: input@lausek.eu
License: UNKNOWN
Keywords: markov,cli
Platform: UNKNOWN
Classifier: License :: OSI Approved :: GNU General Public License v3 (GPLv3)
Classifier: Programming Language :: Python
Classifier: Programming Language :: Python :: 3.7
Classifier: Topic :: Text Processing :: Linguistic
